{
	"$schema": "http://schema.management.azure.com/schemas/2015-01-01/deploymentTemplate.json#",
	"contentVersion": "1.0.0.0",
	"parameters": {
		"factoryName": {
			"type": "string",
			"metadata": "Data Factory Name",
			"defaultValue": "adfv2-dt-datamovment"
		}
	},
	"variables": {
		"factoryId": "[concat('Microsoft.DataFactory/factories/', parameters('factoryName'))]"
	},
	"resources": [
		{
			"name": "[concat(parameters('factoryName'), '/tblProcessTypeDimensionDS')]",
			"type": "Microsoft.DataFactory/factories/datasets",
			"apiVersion": "2018-06-01",
			"properties": {
				"linkedServiceName": {
					"referenceName": "ProcessProd",
					"type": "LinkedServiceReference"
				},
				"annotations": [],
				"type": "SqlServerTable",
				"typeProperties": {
					"tableName": "[concat('[', 'dbo].[tblProcessTypeDimension]')]"
				}
			},
			"dependsOn": []
		},
		{
			"name": "[concat(parameters('factoryName'), '/tblProcessRunHistoryDS')]",
			"type": "Microsoft.DataFactory/factories/datasets",
			"apiVersion": "2018-06-01",
			"properties": {
				"linkedServiceName": {
					"referenceName": "ProcessProd",
					"type": "LinkedServiceReference"
				},
				"annotations": [],
				"type": "SqlServerTable",
				"typeProperties": {
					"tableName": "[concat('[', 'dbo].[tblProcessRunHistory]')]"
				}
			},
			"dependsOn": []
		},
		{
			"name": "[concat(parameters('factoryName'), '/copySinkLoops')]",
			"type": "Microsoft.DataFactory/factories/pipelines",
			"apiVersion": "2018-06-01",
			"properties": {
				"activities": [
					{
						"name": "uspSinkLoop",
						"type": "Lookup",
						"dependsOn": [],
						"policy": {
							"timeout": "7.00:00:00",
							"retry": 0,
							"retryIntervalInSeconds": 30,
							"secureOutput": false,
							"secureInput": false
						},
						"userProperties": [],
						"typeProperties": {
							"source": {
								"type": "SqlSource",
								"sqlReaderStoredProcedureName": "[concat('[', 'adf].[uspSinkLoop]')]",
								"storedProcedureParameters": {
									"sinkgroup": {
										"type": "String",
										"value": {
											"value": "@pipeline().parameters.sinkGroup",
											"type": "Expression"
										}
									}
								}
							},
							"dataset": {
								"referenceName": "AzureSqlTableDB",
								"type": "DatasetReference",
								"parameters": {}
							},
							"firstRowOnly": false
						}
					},
					{
						"name": "ForEachCopySink",
						"type": "ForEach",
						"dependsOn": [
							{
								"activity": "uspSinkLoop",
								"dependencyConditions": [
									"Succeeded"
								]
							}
						],
						"userProperties": [],
						"typeProperties": {
							"items": {
								"value": "@activity('uspSinkLoop').output.value",
								"type": "Expression"
							},
							"activities": [
								{
									"name": "Execute copySink",
									"type": "ExecutePipeline",
									"dependsOn": [],
									"userProperties": [],
									"typeProperties": {
										"pipeline": {
											"referenceName": "copySink",
											"type": "PipelineReference"
										},
										"waitOnCompletion": true,
										"parameters": {
											"sinkName": {
												"value": "@item().sinkName",
												"type": "Expression"
											}
										}
									}
								}
							]
						}
					}
				],
				"parameters": {
					"sinkGroup": {
						"type": "String",
						"defaultValue": "dim_group"
					}
				},
				"folder": {
					"name": "dynamic"
				},
				"annotations": []
			},
			"dependsOn": []
		},
		{
			"name": "[concat(parameters('factoryName'), '/Copy data from on premise SQL Server to SQL Azure1')]",
			"type": "Microsoft.DataFactory/factories/pipelines",
			"apiVersion": "2018-06-01",
			"properties": {
				"description": "Copy data from on premise SQL Server to SQL Azure.\n\nYou can also go to \"Copy Data Tool\" to get the pipeline for more connectors and scenarios.",
				"activities": [
					{
						"name": "tblProcess sqltoazure",
						"description": "Copy data from SQL server to SQL Azure",
						"type": "Copy",
						"dependsOn": [],
						"policy": {
							"timeout": "7.00:00:00",
							"retry": 0,
							"retryIntervalInSeconds": 30,
							"secureOutput": false,
							"secureInput": false
						},
						"userProperties": [],
						"typeProperties": {
							"source": {
								"type": "SqlSource"
							},
							"sink": {
								"type": "SqlSink",
								"writeBatchSize": 10000,
								"preCopyScript": "TRUNCATE TABLE  [dbo].[tblProcess]"
							},
							"enableStaging": false,
							"dataIntegrationUnits": 0
						},
						"inputs": [
							{
								"referenceName": "tblProcess",
								"type": "DatasetReference",
								"parameters": {}
							}
						],
						"outputs": [
							{
								"referenceName": "aztblProcess",
								"type": "DatasetReference",
								"parameters": {}
							}
						]
					},
					{
						"name": "tblProcessStatusDimension",
						"description": "Copy data from SQL server to SQL Azure",
						"type": "Copy",
						"dependsOn": [],
						"policy": {
							"timeout": "7.00:00:00",
							"retry": 0,
							"retryIntervalInSeconds": 30,
							"secureOutput": false,
							"secureInput": false
						},
						"userProperties": [],
						"typeProperties": {
							"source": {
								"type": "SqlSource"
							},
							"sink": {
								"type": "SqlSink",
								"writeBatchSize": 10000,
								"preCopyScript": "TRUNCATE TABLE  [dbo].[tblProcessStatusDimension]"
							},
							"enableStaging": false,
							"dataIntegrationUnits": 0
						},
						"inputs": [
							{
								"referenceName": "tblProcessStatusDimensionDS",
								"type": "DatasetReference",
								"parameters": {}
							}
						],
						"outputs": [
							{
								"referenceName": "tblProcessStatusDimensionDT",
								"type": "DatasetReference",
								"parameters": {}
							}
						]
					},
					{
						"name": "tblProcessTypeDimension",
						"description": "Copy data from SQL server to SQL Azure",
						"type": "Copy",
						"dependsOn": [],
						"policy": {
							"timeout": "7.00:00:00",
							"retry": 0,
							"retryIntervalInSeconds": 30,
							"secureOutput": false,
							"secureInput": false
						},
						"userProperties": [],
						"typeProperties": {
							"source": {
								"type": "SqlSource"
							},
							"sink": {
								"type": "SqlSink",
								"writeBatchSize": 10000,
								"preCopyScript": "TRUNCATE TABLE  [dbo].[tblProcessTypeDimension]"
							},
							"enableStaging": false,
							"dataIntegrationUnits": 0
						},
						"inputs": [
							{
								"referenceName": "tblProcessTypeDimensionDS",
								"type": "DatasetReference",
								"parameters": {}
							}
						],
						"outputs": [
							{
								"referenceName": "tblProcessTypeDimensionDT",
								"type": "DatasetReference",
								"parameters": {}
							}
						]
					},
					{
						"name": "tblProcessRunHistory",
						"description": "Copy data from SQL server to SQL Azure",
						"type": "Copy",
						"dependsOn": [],
						"policy": {
							"timeout": "7.00:00:00",
							"retry": 0,
							"retryIntervalInSeconds": 30,
							"secureOutput": false,
							"secureInput": false
						},
						"userProperties": [],
						"typeProperties": {
							"source": {
								"type": "SqlSource"
							},
							"sink": {
								"type": "SqlSink",
								"writeBatchSize": 10000,
								"preCopyScript": "TRUNCATE TABLE  [dbo].[tblProcessRunHistory]"
							},
							"enableStaging": false,
							"dataIntegrationUnits": 0
						},
						"inputs": [
							{
								"referenceName": "tblProcessRunHistoryDS",
								"type": "DatasetReference",
								"parameters": {}
							}
						],
						"outputs": [
							{
								"referenceName": "tblProcessRunHistoryDT",
								"type": "DatasetReference",
								"parameters": {}
							}
						]
					}
				],
				"annotations": []
			},
			"dependsOn": [
				"[concat(variables('factoryId'), '/datasets/tblProcessTypeDimensionDS')]",
				"[concat(variables('factoryId'), '/datasets/tblProcessRunHistoryDS')]"
			]
		}
	]
}